LICENSE
MANIFEST.in
README.md
setup.py
tap_klaviyo/__init__.py
tap_klaviyo/utils.py
tap_klaviyo.egg-info/PKG-INFO
tap_klaviyo.egg-info/SOURCES.txt
tap_klaviyo.egg-info/dependency_links.txt
tap_klaviyo.egg-info/entry_points.txt
tap_klaviyo.egg-info/requires.txt
tap_klaviyo.egg-info/top_level.txt
tap_klaviyo/schemas/bounce.json
tap_klaviyo/schemas/campaigns.json
tap_klaviyo/schemas/click.json
tap_klaviyo/schemas/clicked_sms.json
tap_klaviyo/schemas/dropped_email.json
tap_klaviyo/schemas/failed_to_deliver.json
tap_klaviyo/schemas/failed_to_deliver_automated_response.json
tap_klaviyo/schemas/global_exclusions.json
tap_klaviyo/schemas/lists.json
tap_klaviyo/schemas/mark_as_spam.json
tap_klaviyo/schemas/open.json
tap_klaviyo/schemas/receive.json
tap_klaviyo/schemas/received_automated_response.json
tap_klaviyo/schemas/received_sms.json
tap_klaviyo/schemas/sent_sms.json
tap_klaviyo/schemas/subscribe_list.json
tap_klaviyo/schemas/subscribed_to_email.json
tap_klaviyo/schemas/subscribed_to_sms.json
tap_klaviyo/schemas/unsub_list.json
tap_klaviyo/schemas/unsubscribe.json
tap_klaviyo/schemas/unsubscribed_from_sms.json
tap_klaviyo/schemas/update_email_preferences.json
tap_klaviyo/schemas/shared/event.json